{
  "name": "example_pipeline",
  "description": "this is a test - note it must reside in a folder with the same name! i.e. example_pipeline",
  "pipeline_type": "I",
  "author": "me",
  "version": "0.0.0",
  "modules": [
    {
      "name": "module_1",
      "description": "step 1",
      "executor": "somefile",
      "index_in_execution_order": 0,
      "options": [
        {
          "display_name": "Cool Selection!",
          "parameter_name": "cs",
          "default_value": "one",
          "user_interaction_type": "string"
        }
      ]
    },

    {
      "name": "module_2",
      "description": "step 2, note the executor for this module must be present in the same location as this file",
      "executor": "somefile2",
      "index_in_execution_order": 1,
      "options": [
        {
          "display_name": "Cool Selection!",
          "parameter_name": "csb",
          "default_value": "",
          "user_interaction_type": "boolean"
        },
        {
          "display_name": "Library Selection!",
          "parameter_name": "l",
          "default_value": "",
          "user_interaction_type": "library"
        }
      ]
    }
  ]
}